<ModOps>
  <ModOp Type="addNextSibling" GUID='127867'>
    <Asset>
      <Template>TownhallBuff</Template>
      <Values>
        <Standard>
          <GUID>1998000005</GUID>
          <Name>Buff de population</Name>
          <IconFilename>data/ui/2kimages/main/3dicons/newspaper/icon_newscategory_satisfaction_good.png</IconFilename>
        </Standard>
        <ItemEffect>
          <EffectTargets>
            <Item>
              <GUID>190762</GUID>
            </Item>
          </EffectTargets>
        </ItemEffect>
        <Text>
          <LocaText>
            <English>
              <Text>Buff de population</Text>
              <Status>Exported</Status>
              <ExportCount>10</ExportCount>
            </English>
          </LocaText>
          <LineID>1998999999</LineID>
        </Text>
        <BuildingUpgrade />
        <Buff />
        <PopulationUpgrade>
          <ResidentsUpgrade>
            <Value>100</Value>
            <Percental>1</Percental>
          </ResidentsUpgrade>
          <InputBenefitModifier>
            <Item>
              <Product>1010200</Product>
              <AdditionalSupply>10</AdditionalSupply>
            </Item>
            <Item>
              <Product>1010213</Product>
              <AdditionalSupply>10</AdditionalSupply>
            </Item>
            <Item>
              <Product>1010217</Product>
              <AdditionalSupply>10</AdditionalSupply>
            </Item>
            <Item>
              <Product>1010353</Product>
              <AdditionalSupply>10</AdditionalSupply>
            </Item>
            <Item>
              <Product>120032</Product>
              <AdditionalSupply>10</AdditionalSupply>
            </Item>
            <Item>
              <Product>1010208</Product>
              <AdditionalSupply>10</AdditionalSupply>
            </Item>
            <Item>
              <Product>120016</Product>
              <AdditionalSupply>10</AdditionalSupply>
            </Item>
            <Item>
              <Product>1010225</Product>
              <AdditionalSupply>10</AdditionalSupply>
            </Item>
            <Item>
              <Product>1010258</Product>
              <AdditionalSupply>10</AdditionalSupply>
            </Item>
            <Item>
              <Product>120033</Product>
              <AdditionalSupply>10</AdditionalSupply>
            </Item>
            <Item>
              <Product>114401</Product>
              <AdditionalSupply>10</AdditionalSupply>
            </Item>
            <Item>
              <Product>117698</Product>
              <AdditionalSupply>10</AdditionalSupply>
            </Item>
            <Item>
              <Product>112705</Product>
              <AdditionalSupply>10</AdditionalSupply>
            </Item>
          </InputBenefitModifier>
        </PopulationUpgrade>
        <ResidenceUpgrade />
        <IncidentInfectableUpgrade />
        <CultureUpgrade>
          <AttractivenessUpgrade>
				    <Value>100</Value>
			    </AttractivenessUpgrade>
        </CultureUpgrade>
        <InfluenceSourceUpgrade />
        <WarehouseUpgrade />
        <DistributionUpgrade />
        <ItemContainerUpgrade />
      </Values>
    </Asset>
  </ModOp>

  <ModOp Type="addNextSibling" GUID='1998000005'>
   <!-- Ancien monde -->
    <Asset>
      <Template>Trigger</Template>
      <Values>
        <Standard>
          <GUID>1998000105</GUID>
          <Name>Buff de population</Name>
        </Standard>
        <Trigger>
          <TriggerCondition>
            <Template>ConditionActiveSession</Template>
            <Values>
              <Condition />
              <ConditionActiveSession>
                <ActiveSession>180023</ActiveSession>
              </ConditionActiveSession>
            </Values>
          </TriggerCondition>
          <TriggerActions>
            <Item>
              <TriggerAction>
                <Template>ActionBuff</Template>
                <Values>
                  <Action />
                  <ActionBuff>
                    <BuffAsset>1998000005</BuffAsset>
                    <AddBuff>0</AddBuff>
                    <BuffProcessingParticipant>1</BuffProcessingParticipant>
                  </ActionBuff>
                </Values>
              </TriggerAction>
            </Item>
            <Item>
              <TriggerAction>
                <Template>ActionBuff</Template>
                <Values>
                  <Action />
                  <ActionBuff>
                    <BuffAsset>1998000005</BuffAsset>
                    <AddBuff>1</AddBuff>
                    <BuffProcessingParticipant>1</BuffProcessingParticipant>
                  </ActionBuff>
                </Values>
              </TriggerAction>
            </Item>
          </TriggerActions>
        </Trigger>
        <TriggerSetup />
      </Values>
    </Asset>

    <!-- Nouvea monde -->
    <Asset>
      <Template>Trigger</Template>
      <Values>
        <Standard>
          <GUID>1998000205</GUID>
          <Name>Buff de population</Name>
        </Standard>
        <Trigger>
          <TriggerCondition>
            <Template>ConditionActiveSession</Template>
            <Values>
              <Condition />
              <ConditionActiveSession>
                <ActiveSession>180025</ActiveSession>
              </ConditionActiveSession>
            </Values>
          </TriggerCondition>
          <TriggerActions>
            <Item>
              <TriggerAction>
                <Template>ActionBuff</Template>
                <Values>
                  <Action />
                  <ActionBuff>
                    <BuffAsset>1998000005</BuffAsset>
                    <AddBuff>0</AddBuff>
                    <BuffProcessingParticipant>1</BuffProcessingParticipant>
                  </ActionBuff>
                </Values>
              </TriggerAction>
            </Item>
            <Item>
              <TriggerAction>
                <Template>ActionBuff</Template>
                <Values>
                  <Action />
                  <ActionBuff>
                    <BuffAsset>1998000005</BuffAsset>
                    <AddBuff>1</AddBuff>
                    <BuffProcessingParticipant>1</BuffProcessingParticipant>
                  </ActionBuff>
                </Values>
              </TriggerAction>
            </Item>
          </TriggerActions>
        </Trigger>
        <TriggerSetup />
      </Values>
    </Asset>
    
    <!-- Trésor oublié -->
    <Asset>
      <Template>Trigger</Template>
      <Values>
        <Standard>
          <GUID>1998000305</GUID>
          <Name>Buff de population</Name>
        </Standard>
        <Trigger>
          <TriggerCondition>
            <Template>ConditionActiveSession</Template>
            <Values>
              <Condition />
              <ConditionActiveSession>
                <ActiveSession>110934</ActiveSession>
              </ConditionActiveSession>
            </Values>
          </TriggerCondition>
          <TriggerActions>
            <Item>
              <TriggerAction>
                <Template>ActionBuff</Template>
                <Values>
                  <Action />
                  <ActionBuff>
                    <BuffAsset>1998000005</BuffAsset>
                    <AddBuff>0</AddBuff>
                    <BuffProcessingParticipant>1</BuffProcessingParticipant>
                  </ActionBuff>
                </Values>
              </TriggerAction>
            </Item>
            <Item>
              <TriggerAction>
                <Template>ActionBuff</Template>
                <Values>
                  <Action />
                  <ActionBuff>
                    <BuffAsset>1998000005</BuffAsset>
                    <AddBuff>1</AddBuff>
                    <BuffProcessingParticipant>1</BuffProcessingParticipant>
                  </ActionBuff>
                </Values>
              </TriggerAction>
            </Item>
          </TriggerActions>
        </Trigger>
        <TriggerSetup />
      </Values>
    </Asset>

    <!-- Afrique -->
    <Asset>
      <Template>Trigger</Template>
      <Values>
        <Standard>
          <GUID>1998000505</GUID>
          <Name>Buff de population</Name>
        </Standard>
        <Trigger>
          <TriggerCondition>
            <Template>ConditionActiveSession</Template>
            <Values>
              <Condition />
              <ConditionActiveSession>
                <ActiveSession>112132</ActiveSession>
              </ConditionActiveSession>
            </Values>
          </TriggerCondition>
          <TriggerActions>
            <Item>
              <TriggerAction>
                <Template>ActionBuff</Template>
                <Values>
                  <Action />
                  <ActionBuff>
                    <BuffAsset>1998000005</BuffAsset>
                    <AddBuff>0</AddBuff>
                    <BuffProcessingParticipant>1</BuffProcessingParticipant>
                  </ActionBuff>
                </Values>
              </TriggerAction>
            </Item>
            <Item>
              <TriggerAction>
                <Template>ActionBuff</Template>
                <Values>
                  <Action />
                  <ActionBuff>
                    <BuffAsset>1998000005</BuffAsset>
                    <AddBuff>1</AddBuff>
                    <BuffProcessingParticipant>1</BuffProcessingParticipant>
                  </ActionBuff>
                </Values>
              </TriggerAction>
            </Item>
          </TriggerActions>
        </Trigger>
        <TriggerSetup />
      </Values>
    </Asset>
  </ModOp>
</ModOps>